data_vision/__init__.py
data_vision/probility_distribution.py
data_vision/scatter.py
excel_operations/__init__.py
excel_operations/read_and_write.py
function_operation/__init__.py
function_operation/linear_fit.py
function_operation/poly_fit.py
zhhmathmodel/__init__.py
zhhmathmodel/linear_fit.py
zhhmathmodel/poly_fit.py
zhhmathmodel/probility_distribution.py
zhhmathmodel/read_and_write.py
zhhmathmodel/scatter.py
zhhmathmodel-1.1.0.dist-info/LICENSE.txt
zhhmathmodel-1.1.0.dist-info/METADATA
zhhmathmodel-1.1.0.dist-info/WHEEL
zhhmathmodel-1.1.0.dist-info/top_level.txt
zhhmathmodel-1.1.0.dist-info/RECORD
